nnusf/__init__.py
nnusf/cli/__init__.py
nnusf/cli/base.py
nnusf/cli/data.py
nnusf/cli/extra.py
nnusf/cli/fit.py
nnusf/cli/log.py
nnusf/cli/plot.py
nnusf/cli/report.py
nnusf/cli/theory.py
nnusf/data/__init__.py
nnusf/data/coefficients.py
nnusf/data/combine_tables.py
nnusf/data/filters.py
nnusf/data/loader.py
nnusf/data/matching_grids.py
nnusf/data/utils.py
nnusf/filters/filter_bebcwa59.py
nnusf/filters/filter_ccfr.py
nnusf/filters/filter_cdhsw.py
nnusf/filters/filter_charm.py
nnusf/filters/filter_chorus.py
nnusf/filters/filter_nutev.py
nnusf/get/__init__.py
nnusf/get/base.py
nnusf/get/gettheory.py
nnusf/get/log.py
nnusf/lhapdf/__init__.py
nnusf/lhapdf/dump_grids.py
nnusf/lhapdf/utils.py
nnusf/plot/__init__.py
nnusf/plot/covmat.py
nnusf/plot/fit.py
nnusf/plot/kinematics.py
nnusf/plot/matching.py
nnusf/plot/sf.py
nnusf/plot/sfs_lhapdf.py
nnusf/plot/th_covmat.py
nnusf/plot/utils.py
nnusf/plotstyle.mplstyle
nnusf/reports/__init__.py
nnusf/reports/assets/index.html
nnusf/reports/assets/report.css
nnusf/reports/genfiles.py
nnusf/reports/genhtml.py
nnusf/scripts/__init__.py
nnusf/scripts/gettheory.py
nnusf/scripts/integrate.py
nnusf/scripts/isoscalar.py
nnusf/sffit/__init__.py
nnusf/sffit/callbacks.py
nnusf/sffit/compute_expchi2.py
nnusf/sffit/layers.py
nnusf/sffit/load_data.py
nnusf/sffit/load_fit_data.py
nnusf/sffit/model_gen.py
nnusf/sffit/postfit.py
nnusf/sffit/run_sffit.py
nnusf/sffit/scaling.py
nnusf/sffit/sum_rules.py
nnusf/sffit/train_model.py
nnusf/sffit/utils.py
nnusf/theory/__init__.py
nnusf/theory/assets/genie.hdf5
nnusf/theory/assets/theory_nnusf.yaml
nnusf/theory/bodek_yang/__init__.py
nnusf/theory/bodek_yang/cuts.py
nnusf/theory/bodek_yang/load.py
nnusf/theory/bodek_yang/runcards.py
nnusf/theory/compare_to_data.py
nnusf/theory/data_vs_theory/__init__.py
nnusf/theory/data_vs_theory/runcards.py
nnusf/theory/defs.py
nnusf/theory/grids.py
nnusf/theory/highq/__init__.py
nnusf/theory/highq/load.py
nnusf/theory/highq/runcards.py
nnusf/theory/predictions.py
nnusf-0.3.0.dist-info/LICENSE
nnusf-0.3.0.dist-info/METADATA
nnusf-0.3.0.dist-info/WHEEL
nnusf-0.3.0.dist-info/entry_points.txt
nnusf-0.3.0.dist-info/RECORD
