Metadata-Version: 2.1
Name: nnusf
Version: 0.3.0
Summary: Predictions for all-energy neutrino structure functions
Home-page: https://github.com/NNPDF/nnusf
Author: Alessandro Candido
Author-email: candido.ale@gmail.com
Requires-Python: >=3.9,<3.11
Classifier: License :: OSI Approved :: GNU General Public License v3 (GPLv3)
Classifier: Programming Language :: Python
Classifier: Programming Language :: Python :: 3
Classifier: Programming Language :: Python :: 3.9
Classifier: Programming Language :: Python :: 3.10
Classifier: Topic :: Scientific/Engineering
Classifier: Topic :: Scientific/Engineering :: Physics
Requires-Dist: PyYAML (>=6.0,<7.0)
Requires-Dist: SQLAlchemy (>=1.4.39,<2.0.0)
Requires-Dist: appdirs (>=1.4.4,<2.0.0)
Requires-Dist: banana-hep (>=0.6.6,<0.7.0)
Requires-Dist: click (>=8.1.3,<9.0.0)
Requires-Dist: greenlet (>=1.1.2,<2.0.0)
Requires-Dist: h5py (>=3.7.0,<4.0.0)
Requires-Dist: matplotlib (>=3.5.2,<4.0.0)
Requires-Dist: pandas (>=1.4.2,<2.0.0)
Requires-Dist: particle (>=0.21.2,<0.22.0)
Requires-Dist: pendulum (>=2.1.2,<3.0.0)
Requires-Dist: pineappl (>=0.5.0,<0.6.0)
Requires-Dist: pygit2 (>=1.10.1,<2.0.0)
Requires-Dist: pylint (>=2.14.4,<3.0.0)
Requires-Dist: pytzdata (>=2020.1,<2021.0)
Requires-Dist: rich (>=12.5.1,<13.0.0)
Requires-Dist: scipy (>=1.8.1,<2.0.0)
Requires-Dist: seaborn (==0.12.2)
Requires-Dist: setuptools (>=65.5.1,<66.0.0)
Requires-Dist: tensorflow (<2.11.2)
Requires-Dist: termcolor (==1.1.0)
Requires-Dist: yadism (==0.12.3)
Project-URL: Repository, https://github.com/NNPDF/nnusf
